shipmi/__init__.py
shipmi/config.py
shipmi/control.py
shipmi/exception.py
shipmi/log.py
shipmi/manager.py
shipmi/provider.py
shipmi/utils.py
shipmi/vbmc.py
shipmi/cmd/__init__.py
shipmi/cmd/shipmi.py
shipmi/cmd/shipmid.py
shipmi/providers/proxmox-qm.conf
shipmi/tests/__init__.py
shipmi/tests/unit/__init__.py
shipmi/tests/unit/base.py
shipmi/tests/unit/test_config.py
shipmi/tests/unit/test_control.py
shipmi/tests/unit/test_manager.py
shipmi/tests/unit/test_provider.py
shipmi/tests/unit/test_utils.py
shipmi/tests/unit/test_vbmc.py
shipmi/tests/unit/utils.py
shipmi/tests/unit/cmd/__init__.py
shipmi/tests/unit/cmd/test_shipmi.py
shipmi/tests/unit/cmd/test_shipmid.py
shipmi/tests/unit/providers/__init__.py
shipmi/tests/unit/providers/test.conf
shipmi-3.0.1.dist-info/AUTHORS
shipmi-3.0.1.dist-info/LICENSE
shipmi-3.0.1.dist-info/METADATA
shipmi-3.0.1.dist-info/WHEEL
shipmi-3.0.1.dist-info/entry_points.txt
shipmi-3.0.1.dist-info/top_level.txt
shipmi-3.0.1.dist-info/RECORD
