Metadata-Version: 2.1
Name: shipmi
Version: 3.0.1
Summary: A virtual BMC for executing shell scripts using IPMI commands.
Home-page: https://github.com/lion7/shipmi
Author: Gerard de Leeuw
Author-email: shipmi@leeuwit.nl
License: UNKNOWN
Project-URL: Bug Tracker, https://github.com/pypa/sampleproject/issues
Platform: UNKNOWN
Classifier: Intended Audience :: Information Technology
Classifier: Intended Audience :: System Administrators
Classifier: License :: OSI Approved :: Apache Software License
Classifier: Operating System :: POSIX :: Linux
Classifier: Programming Language :: Python
Classifier: Programming Language :: Python :: Implementation :: CPython
Classifier: Programming Language :: Python :: 3 :: Only
Classifier: Programming Language :: Python :: 3
Classifier: Programming Language :: Python :: 3.8
Classifier: Programming Language :: Python :: 3.9
Requires-Python: >=3.8
License-File: LICENSE
License-File: AUTHORS
Requires-Dist: pyghmi (>=1.5.33)
Requires-Dist: cliff (>=3.10.0)
Requires-Dist: pyzmq (>=22.3.0)
